ocsf_schema_compiler/__init__.py
ocsf_schema_compiler/__main__.py
ocsf_schema_compiler/compiler.py
ocsf_schema_compiler/exceptions.py
ocsf_schema_compiler/jsonish.py
ocsf_schema_compiler/legacy_mode.py
ocsf_schema_compiler/structured_read.py
ocsf_schema_compiler/utils.py
ocsf_schema_compiler-0.9.7.dist-info/entry_points.txt
ocsf_schema_compiler-0.9.7.dist-info/licenses/LICENSE
ocsf_schema_compiler-0.9.7.dist-info/WHEEL
ocsf_schema_compiler-0.9.7.dist-info/METADATA
ocsf_schema_compiler-0.9.7.dist-info/RECORD
