Metadata-Version: 2.4
Name: ocsf_schema_compiler
Version: 0.9.7
Summary: Compile an Open Cybersecurity Schema Framework (OCSF) schema.
Keywords: compiler,ocsf,schema,ocsf-schema
Author-email: Rick Mouritzen <rick@rickmode.com>
Requires-Python: >= 3.14
License-Expression: Apache-2.0
Classifier: Development Status :: 4 - Beta
Classifier: Intended Audience :: Developers
Classifier: Operating System :: OS Independent
Classifier: Programming Language :: Python
Classifier: Programming Language :: Python :: 3
Classifier: Programming Language :: Python :: 3.14
Classifier: Topic :: Software Development :: Build Tools
Classifier: Topic :: Software Development :: Compilers
Classifier: Topic :: Software Development :: Libraries
Classifier: Topic :: Software Development :: Libraries :: Python Modules
License-File: LICENSE
Requires-Dist: basedpyright ; extra == "dev"
Requires-Dist: ruff ; extra == "dev"
Project-URL: Home, https://github.com/ocsf/ocsf-schema-compiler
Project-URL: Issues, https://github.com/ocsf/ocsf-schema-compiler/issues
Project-URL: Repository, https://github.com/ocsf/ocsf-schema-compiler.git
Provides-Extra: dev
